femtetutils/__init__.py
femtetutils/__main__.py
femtetutils/constant.py
femtetutils/util.py
femtetutils-1.0.0.dist-info/METADATA
femtetutils-1.0.0.dist-info/WHEEL
femtetutils-1.0.0.dist-info/top_level.txt
femtetutils-1.0.0.dist-info/RECORD
