Metadata-Version: 2.1
Name: femtetutils
Version: 1.0.0
Summary: Femtet Python Utilities
Author: Murata Manufacturing Co., Ltd.
License: MIT
Requires-Python: >=3.8
Requires-Dist: pywin32 >=305
